inkly/__init__.py
inkly/__main__.py
inkly/cli.py
inkly/generator.py
inkly/parser.py
inkly/serve.py
inkly/generators/__init__.py
inkly/generators/base.py
inkly/generators/client.py
inkly/generators/flask_server.py
inkly/generators/server.py
inkly/generators/templates/__init__.py
inkly/generators/templates/client.py
inkly/generators/templates/flask.py
inkly/generators/templates/mock.py
inkly/generators/templates/models.py
inkly/generators/templates/server.py
inkly-1.0.1.dist-info/METADATA
inkly-1.0.1.dist-info/WHEEL
inkly-1.0.1.dist-info/entry_points.txt
inkly-1.0.1.dist-info/RECORD
