Metadata-Version: 2.4
Name: inkly
Version: 1.0.1
Summary: OpenAPI client & server code generator
Project-URL: Homepage, https://github.com/inkly-team/inkly
Project-URL: Repository, https://github.com/inkly-team/inkly
Project-URL: Documentation, https://github.com/inkly-team/inkly
Project-URL: Issues, https://github.com/inkly-team/inkly/issues
Author-email: Inkly Team <info@inkly.dev>
License: MIT
Keywords: client,code-generation,fastapi,openapi,pydantic,server
Classifier: Development Status :: 4 - Beta
Classifier: Intended Audience :: Developers
Classifier: License :: OSI Approved :: MIT License
Classifier: Programming Language :: Python :: 3
Classifier: Programming Language :: Python :: 3.12
Classifier: Programming Language :: Python :: 3.13
Classifier: Topic :: Internet :: WWW/HTTP :: HTTP Servers
Classifier: Topic :: Software Development :: Code Generators
Classifier: Typing :: Typed
Requires-Python: >=3.12
Requires-Dist: click>=8.0.0
Requires-Dist: fastapi>=0.100.0
Requires-Dist: httpx>=0.25.0
Requires-Dist: jinja2>=3.1.0
Requires-Dist: pydantic>=2.5.0
Requires-Dist: pyyaml>=6.0
Requires-Dist: rich>=13.0.0
Requires-Dist: uvicorn[standard]>=0.20.0
Provides-Extra: dev
Requires-Dist: pre-commit>=3.6.0; extra == 'dev'
Requires-Dist: pyright>=1.1.350; extra == 'dev'
Requires-Dist: pytest-asyncio>=0.23.0; extra == 'dev'
Requires-Dist: pytest-cov>=4.0.0; extra == 'dev'
Requires-Dist: pytest>=8.0.0; extra == 'dev'
Requires-Dist: ruff>=0.3.0; extra == 'dev'
